mappyfile/__init__.py
mappyfile/cli.py
mappyfile/dictutils.py
mappyfile/mapfile.lark
mappyfile/ordereddict.py
mappyfile/parser.py
mappyfile/pprint.py
mappyfile/py.typed
mappyfile/quoter.py
mappyfile/tokens.py
mappyfile/transformer.py
mappyfile/utils.py
mappyfile/validator.py
mappyfile/schemas/class.json
mappyfile/schemas/cluster.json
mappyfile/schemas/color.json
mappyfile/schemas/composite.json
mappyfile/schemas/config.json
mappyfile/schemas/connectionoptions.json
mappyfile/schemas/debug.json
mappyfile/schemas/env.json
mappyfile/schemas/expression.json
mappyfile/schemas/extent.json
mappyfile/schemas/feature.json
mappyfile/schemas/grid.json
mappyfile/schemas/hex.json
mappyfile/schemas/hex2.json
mappyfile/schemas/identify.json
mappyfile/schemas/join.json
mappyfile/schemas/label.json
mappyfile/schemas/layer.json
mappyfile/schemas/leader.json
mappyfile/schemas/legend.json
mappyfile/schemas/map.json
mappyfile/schemas/maps.json
mappyfile/schemas/metadata.json
mappyfile/schemas/onoff.json
mappyfile/schemas/outputformat.json
mappyfile/schemas/plugins.json
mappyfile/schemas/points.json
mappyfile/schemas/position.json
mappyfile/schemas/projection.json
mappyfile/schemas/querymap.json
mappyfile/schemas/reference.json
mappyfile/schemas/rgb.json
mappyfile/schemas/scalebar.json
mappyfile/schemas/scaletoken.json
mappyfile/schemas/sizeunits.json
mappyfile/schemas/style.json
mappyfile/schemas/symbol.json
mappyfile/schemas/symbolset.json
mappyfile/schemas/units.json
mappyfile/schemas/validation.json
mappyfile/schemas/web.json
mappyfile/schemas/yesno.json
mappyfile-1.1.1.dist-info/licenses/LICENSE
mappyfile-1.1.1.dist-info/METADATA
mappyfile-1.1.1.dist-info/WHEEL
mappyfile-1.1.1.dist-info/entry_points.txt
mappyfile-1.1.1.dist-info/top_level.txt
mappyfile-1.1.1.dist-info/RECORD
