Metadata-Version: 2.4
Name: mappyfile
Version: 1.1.1
Summary: A pure Python MapFile parser for working with MapServer
Home-page: http://github.com/geographika/mappyfile
Author: Seth Girvin
Author-email: sethg@geographika.co.uk
License: MIT
Classifier: Development Status :: 5 - Production/Stable
Classifier: License :: OSI Approved :: MIT License
Classifier: Programming Language :: Python :: 3.8
Classifier: Programming Language :: Python :: 3.9
Classifier: Programming Language :: Python :: 3.10
Classifier: Programming Language :: Python :: 3.11
Classifier: Programming Language :: Python :: 3.12
Classifier: Programming Language :: Python :: 3.13
Classifier: Intended Audience :: Developers
Classifier: Topic :: Scientific/Engineering :: GIS
Classifier: Topic :: Text Processing :: Linguistic
Classifier: Topic :: Software Development :: Build Tools
License-File: LICENSE
Requires-Dist: lark>=1.1.5
Requires-Dist: jsonschema>=4.18.0
Requires-Dist: click
Provides-Extra: lark-cython
Requires-Dist: lark_cython>=0.0.14; extra == "lark-cython"
Dynamic: author
Dynamic: author-email
Dynamic: classifier
Dynamic: description
Dynamic: description-content-type
Dynamic: home-page
Dynamic: license
Dynamic: license-file
Dynamic: provides-extra
Dynamic: requires-dist
Dynamic: summary
